date_management/__init__.py
date_management/date_management.py
RR_Date_Management-0.0.3.dist-info/LICENSE
RR_Date_Management-0.0.3.dist-info/METADATA
RR_Date_Management-0.0.3.dist-info/WHEEL
RR_Date_Management-0.0.3.dist-info/top_level.txt
RR_Date_Management-0.0.3.dist-info/RECORD
